{
  "version": 3,
  "middleware": {
    "/": {
      "files": [
        "server/edge-runtime-webpack.js",
        "server/middleware.js"
      ],
      "name": "middleware",
      "page": "/",
      "matchers": [
        {
          "regexp": "^(?:\\/(_next\\/data\\/[^/]{1,}))?(?:\\/((?!_next\\/static|_next\\/image|favicon.ico|.*\\.(?:svg|png|jpg|jpeg|gif|webp)$).*))(\\.json)?[\\/#\\?]?$",
          "originalSource": "/((?!_next/static|_next/image|favicon.ico|.*\\.(?:svg|png|jpg|jpeg|gif|webp)$).*)"
        }
      ],
      "wasm": [],
      "assets": [],
      "env": {
        "__NEXT_BUILD_ID": "ZunUVwDox1SDtbVW4tsvt",
        "NEXT_SERVER_ACTIONS_ENCRYPTION_KEY": "aCleMXyyRO4AFH/Hc06hIXUYFCZSsXfrIkPhRIXhQRs=",
        "__NEXT_PREVIEW_MODE_ID": "022cb4b367d549bfb70b6824264dc4fa",
        "__NEXT_PREVIEW_MODE_ENCRYPTION_KEY": "5210f703f6dbf0631ba584848b69522d9559a8acab0dfb51d5bb6cf8dc2a0e98",
        "__NEXT_PREVIEW_MODE_SIGNING_KEY": "c33bb56fc4b096640d2b0477e7ee75010bb1adc039213f91a16a1719346d9483"
      }
    }
  },
  "functions": {},
  "sortedMiddleware": [
    "/"
  ]
}